fbnsdkutilities/__init__.py
fbnsdkutilities/__version__.py
fbnsdkutilities/tcp/__init__.py
fbnsdkutilities/tcp/tcp_keep_alive_probes.py
fbnsdkutilities/utilities/__init__.py
fbnsdkutilities/utilities/api_client_builder.py
fbnsdkutilities/utilities/api_client_factory.py
fbnsdkutilities/utilities/api_configuration.py
fbnsdkutilities/utilities/api_configuration_loader.py
fbnsdkutilities/utilities/proxy_config.py
fbnsdkutilities/utilities/refreshing_token.py
fbnsdkutilities/utilities/retry.py
finbourne_sdk_utilities-0.0.10.dist-info/METADATA
finbourne_sdk_utilities-0.0.10.dist-info/WHEEL
finbourne_sdk_utilities-0.0.10.dist-info/top_level.txt
finbourne_sdk_utilities-0.0.10.dist-info/RECORD
