Metadata-Version: 2.1
Name: finbourne-sdk-utilities
Version: 0.0.10
Summary: Utilities for FINBOURNE Python SDKs
Home-page: https://github.com/finbourne/sdk-utilities-python
Author: FINBOURNE Technology
Author-email: engineering@finbourne.com
License: MIT
Keywords: OpenAPI,FINBOURNE,LUSID,SDK
Platform: UNKNOWN
Requires-Dist: urllib3 (>=1.15.1)
